cdktf_aws_secure/__init__.py
cdktf_aws_secure/py.typed
cdktf_aws_secure/_jsii/__init__.py
cdktf_aws_secure/_jsii/cdktf-aws-secure@2.0.1.jsii.tgz
cdktf_aws_secure-2.0.1.dist-info/LICENSE
cdktf_aws_secure-2.0.1.dist-info/METADATA
cdktf_aws_secure-2.0.1.dist-info/WHEEL
cdktf_aws_secure-2.0.1.dist-info/top_level.txt
cdktf_aws_secure-2.0.1.dist-info/RECORD
