Metadata-Version: 2.1
Name: cdktf-aws-secure
Version: 2.0.1
Summary: High level CDKTF construct to provision secure configurations with AWS
Home-page: https://github.com/shazi7804/cdktf-aws-secure-constructs.git
Author: Scott Liao<shazi7804@gmail.com>
License: Apache-2.0
Project-URL: Source, https://github.com/shazi7804/cdktf-aws-secure-constructs.git
Platform: UNKNOWN
Classifier: Intended Audience :: Developers
Classifier: Operating System :: OS Independent
Classifier: Programming Language :: JavaScript
Classifier: Programming Language :: Python :: 3 :: Only
Classifier: Programming Language :: Python :: 3.6
Classifier: Programming Language :: Python :: 3.7
Classifier: Programming Language :: Python :: 3.8
Classifier: Programming Language :: Python :: 3.9
Classifier: Typing :: Typed
Classifier: Development Status :: 5 - Production/Stable
Classifier: License :: OSI Approved
Requires-Python: >=3.6
Requires-Dist: cdktf-cdktf-provider-aws (<2.0.0,>=1.0.59)
Requires-Dist: cdktf (<0.4.0,>=0.3.0)
Requires-Dist: constructs (<4.0.0,>=3.0.0)
Requires-Dist: jsii (<2.0.0,>=1.29.0)
Requires-Dist: publication (>=0.0.3)
